LICENSE
MANIFEST.in
README.md
setup.cfg
setup.py
tap_urban_airship/__init__.py
tap_urban_airship/transform.py
tap_urban_airship.egg-info/PKG-INFO
tap_urban_airship.egg-info/SOURCES.txt
tap_urban_airship.egg-info/dependency_links.txt
tap_urban_airship.egg-info/entry_points.txt
tap_urban_airship.egg-info/requires.txt
tap_urban_airship.egg-info/top_level.txt
tap_urban_airship/schemas/channels.json
tap_urban_airship/schemas/lists.json
tap_urban_airship/schemas/named_users.json
tap_urban_airship/schemas/segments.json