Metadata-Version: 1.1
Name: tap-urban-airship
Version: 0.8.1
Summary: Singer.io tap for extracting data from the Urban Airship API
Home-page: http://singer.io
Author: Stitch
Author-email: UNKNOWN
License: UNKNOWN
Platform: UNKNOWN
Classifier: Programming Language :: Python :: 3 :: Only
